df_to_dictionary/__init__.py
df_to_dictionary/main.py
df_to_dictionary-0.5.dist-info/LICENSE.txt
df_to_dictionary-0.5.dist-info/METADATA
df_to_dictionary-0.5.dist-info/WHEEL
df_to_dictionary-0.5.dist-info/top_level.txt
df_to_dictionary-0.5.dist-info/RECORD
