Metadata-Version: 2.1
Name: df-to-dictionary
Version: 0.5
Author: Nilesh Shinde
License-File: LICENSE.txt
Requires-Dist: numpy (==1.23.5)
Requires-Dist: pandas (==1.5.2)
Requires-Dist: python-dateutil (==2.8.2)
Requires-Dist: pytz (==2022.6)
Requires-Dist: six (==1.16.0)
